phabricator/__init__.py
phabricator/py.typed
fab-3.1.0.dist-info/COPYING
fab-3.1.0.dist-info/COPYING.LESSER
fab-3.1.0.dist-info/METADATA
fab-3.1.0.dist-info/WHEEL
fab-3.1.0.dist-info/top_level.txt
fab-3.1.0.dist-info/RECORD
