Metadata-Version: 2.1
Name: fab
Version: 3.1.0
Summary: Wrapper around Phabricator API
Home-page: https://github.com/legoktm/fab
Author: Kunal Mehta
Author-email: legoktm@member.fsf.org
License: LGPL-3.0-or-later
Platform: UNKNOWN
Requires-Python: >=3.4
Requires-Dist: requests
